{
  "id": "2026-05-17-github-trending-supertonic",
  "title": "supertone-inc/supertonic - 端侧多语言 TTS 引擎",
  "source_url": "https://github.com/supertone-inc/supertonic",
  "source_type": "github_trending",
  "summary": "基于 ONNX 的端侧 TTS 引擎，多语言、低延迟、完全离线运行，Swift 编写优化 Apple 生态，适合隐私敏感场景和移动端 AI 语音部署",
  "tags": ["Tool", "Open Source", "Inference", "Multilingual"],
  "status": "reviewed",
  "created_at": "2026-05-17T09:45:00+08:00",
  "push_channels": ["telegram", "feishu"],
  "push_status": {
    "telegram": "pending",
    "feishu": "pending"
  }
}
